accelbyte_py_sdk/api/ams/__init__.py
accelbyte_py_sdk/api/ams/errors.py
accelbyte_py_sdk/api/ams/models/__init__.py
accelbyte_py_sdk/api/ams/models/api_account_create_request.py
accelbyte_py_sdk/api/ams/models/api_account_create_response.py
accelbyte_py_sdk/api/ams/models/api_account_limits.py
accelbyte_py_sdk/api/ams/models/api_account_link_request.py
accelbyte_py_sdk/api/ams/models/api_account_link_response.py
accelbyte_py_sdk/api/ams/models/api_account_link_token_response.py
accelbyte_py_sdk/api/ams/models/api_account_response.py
accelbyte_py_sdk/api/ams/models/api_ams_regions_response.py
accelbyte_py_sdk/api/ams/models/api_artifact_list_response.py
accelbyte_py_sdk/api/ams/models/api_artifact_response.py
accelbyte_py_sdk/api/ams/models/api_artifact_sampling_rule.py
accelbyte_py_sdk/api/ams/models/api_artifact_type_sampling_rules.py
accelbyte_py_sdk/api/ams/models/api_artifact_url_response.py
accelbyte_py_sdk/api/ams/models/api_artifact_usage_response.py
accelbyte_py_sdk/api/ams/models/api_capacity.py
accelbyte_py_sdk/api/ams/models/api_coredump_sampling_rules.py
accelbyte_py_sdk/api/ams/models/api_development_server_configuration_create_request.py
accelbyte_py_sdk/api/ams/models/api_development_server_configuration_create_response.py
accelbyte_py_sdk/api/ams/models/api_development_server_configuration_get_response.py
accelbyte_py_sdk/api/ams/models/api_development_server_configuration_list_response.py
accelbyte_py_sdk/api/ams/models/api_development_server_configuration_update_request.py
accelbyte_py_sdk/api/ams/models/api_ds_history_event.py
accelbyte_py_sdk/api/ams/models/api_ds_history_list.py
accelbyte_py_sdk/api/ams/models/api_ds_host_configuration.py
accelbyte_py_sdk/api/ams/models/api_ds_host_configuration_parameters.py
accelbyte_py_sdk/api/ams/models/api_fleet_artifacts_sample_rules.py
accelbyte_py_sdk/api/ams/models/api_fleet_bulk_action_error_item_response.py
accelbyte_py_sdk/api/ams/models/api_fleet_bulk_delete_request.py
accelbyte_py_sdk_service_ams-0.25.0.dist-info/METADATA
accelbyte_py_sdk_service_ams-0.25.0.dist-info/WHEEL
accelbyte_py_sdk_service_ams-0.25.0.dist-info/top_level.txt
accelbyte_py_sdk_service_ams-0.25.0.dist-info/RECORD
