Metadata-Version: 2.4
Name: accelbyte-py-sdk-service-ams
Version: 0.25.0
Summary: AccelByte Python SDK - Fleet Commander
Requires-Python: >=3.9
Requires-Dist: accelbyte-py-sdk-core
